sentence_classifier/BERT.py
sentence_classifier/NLP_utils.py
sentence_classifier/NN.py
sentence_classifier/__init__.py
sentence_classifier/sentence_classifier.py
sentence_classifier/simple_classifiers.py
sentence_classifier-0.1.1.dist-info/AUTHORS.rst
sentence_classifier-0.1.1.dist-info/LICENSE
sentence_classifier-0.1.1.dist-info/METADATA
sentence_classifier-0.1.1.dist-info/WHEEL
sentence_classifier-0.1.1.dist-info/top_level.txt
sentence_classifier-0.1.1.dist-info/RECORD
