Metadata-Version: 2.1
Name: sentence-classifier
Version: 0.1.1
Summary: to fine-tune various algorithms on sentence classification tasks
Home-page: https://github.com/KCLAurelie/sentence_classifier
Author: Aurelie Mascio
Author-email: gurugumawaru@gmail.com
License: MIT license
Keywords: sentence_classifier
Platform: UNKNOWN
Classifier: Development Status :: 2 - Pre-Alpha
Classifier: Intended Audience :: Developers
Classifier: License :: OSI Approved :: MIT License
Classifier: Natural Language :: English
Classifier: Programming Language :: Python :: 3
Classifier: Programming Language :: Python :: 3.5
Classifier: Programming Language :: Python :: 3.6
Classifier: Programming Language :: Python :: 3.7
Classifier: Programming Language :: Python :: 3.8
Requires-Python: >=3.5
